hexgrid/__init__.py
hexgrid/apps.py
hexgrid/migrations/0001_create_hex.py
hexgrid/migrations/__init__.py
hexgrid/models.py
django_hexgrid-0.1.0.dist-info/METADATA
django_hexgrid-0.1.0.dist-info/WHEEL
django_hexgrid-0.1.0.dist-info/RECORD
